langiso639/__init__.py
langiso639/languages_utf-8.txt
langiso639-0.2.3.dist-info/licenses/LICENSE
langiso639-0.2.3.dist-info/METADATA
langiso639-0.2.3.dist-info/WHEEL
langiso639-0.2.3.dist-info/top_level.txt
langiso639-0.2.3.dist-info/RECORD
