Metadata-Version: 2.4
Name: langiso639
Version: 0.2.3
Summary: ISO639-3 support for Python.
Home-page: https://github.com/jgarcial/iso639-python
Author: Jaime Garcia Llopis
Author-email: jaime.garcia.llopis@gmail.com
License: MIT
License-File: LICENSE
Provides-Extra: full
Dynamic: author
Dynamic: author-email
Dynamic: description
Dynamic: description-content-type
Dynamic: home-page
Dynamic: license
Dynamic: license-file
Dynamic: provides-extra
Dynamic: summary
